MANIFEST.in
README.txt
buildout.cfg
minitage.cfg
setup.cfg
setup.py
docs/HISTORY.txt
docs/LICENSE.GPL
docs/LICENSE.txt
src/buildout/__init__.py
src/buildout.minitagificator.egg-info/PKG-INFO
src/buildout.minitagificator.egg-info/SOURCES.txt
src/buildout.minitagificator.egg-info/dependency_links.txt
src/buildout.minitagificator.egg-info/entry_points.txt
src/buildout.minitagificator.egg-info/namespace_packages.txt
src/buildout.minitagificator.egg-info/not-zip-safe
src/buildout.minitagificator.egg-info/requires.txt
src/buildout.minitagificator.egg-info/top_level.txt
src/buildout/minitagificator/__init__.py
src/buildout/minitagificator/minitagificator.py
src/buildout/minitagificator/minitagificator.txt
src/buildout/minitagificator/tests.py