Metadata-Version: 1.1
Name: buildout.minitagificator
Version: 2.4.29
Summary: A buildout extension to replace buildout part by minitage interesant ones sponsored by Makina Corpus
Home-page: https://github.com/minitage/buildout.minitagificator
Author: Mathieu Pasquet
Author-email: kiorky@cryptelium.net
License: GPL
Platform: UNKNOWN
Classifier: Framework :: Buildout
Classifier: Framework :: Plone
Classifier: Programming Language :: Python
Classifier: Topic :: Software Development :: Libraries :: Python Modules
